Simple_Dropbox/Script.py
Simple_Dropbox/__init__.py
Simple_Dropbox-1.5.2.dist-info/LICENSE
Simple_Dropbox-1.5.2.dist-info/METADATA
Simple_Dropbox-1.5.2.dist-info/WHEEL
Simple_Dropbox-1.5.2.dist-info/top_level.txt
Simple_Dropbox-1.5.2.dist-info/RECORD
